knowl/__init__.py
knowl/database.py
knowl/databaseAPI.py
knowl/db_config.py
knowl-0.1.1.dist-info/LICENSE
knowl-0.1.1.dist-info/METADATA
knowl-0.1.1.dist-info/WHEEL
knowl-0.1.1.dist-info/top_level.txt
knowl-0.1.1.dist-info/RECORD
