Metadata-Version: 2.1
Name: knowl
Version: 0.1.1
Summary: Knowledge Ontology-based OOP language
Home-page: UNKNOWN
Author: Imitation Learning Group CIIRC CVUT
Maintainer-email: radoslav.skoviera@cvut.cz
License: Mozilla Public License Version 2.0
Platform: UNKNOWN
Classifier: Programming Language :: Python :: 3
Classifier: Programming Language :: Python :: 3.6
Classifier: Programming Language :: Python :: 3.7
Classifier: Development Status :: 3 - Alpha
Classifier: Intended Audience :: Education
Classifier: Intended Audience :: Information Technology
Classifier: Intended Audience :: Science/Research
Classifier: Intended Audience :: Developers
Classifier: Topic :: Scientific/Engineering :: Artificial Intelligence
Classifier: Topic :: Database
Classifier: License :: OSI Approved :: Mozilla Public License 2.0 (MPL 2.0)
Requires-Dist: pyyaml (>=5)
Requires-Dist: rdflib (>=4.2.2)
Requires-Dist: rdflib-sqlalchemy (>=0.3.8)
Provides-Extra: test
Requires-Dist: pytest ; extra == 'test'
Requires-Dist: coverage ; extra == 'test'
Requires-Dist: pytest-cov ; extra == 'test'
Requires-Dist: pyyaml ; extra == 'test'
Requires-Dist: codecov ; extra == 'test'
